mcot/__init__.py
mcot/pipe/README.rst
mcot/pipe/VERSION
mcot/pipe/__init__.py
mcot/pipe/datalad.py
mcot/pipe/job.py
mcot/pipe/pipeline.py
mcot/pipe/concrete/__init__.py
mcot/pipe/concrete/core.py
mcot/pipe/concrete/dippi.py
mcot/pipe/concrete/dmri.py
mcot/pipe/concrete/trees/dippi.tree
mcot/pipe/concrete/trees/dippi_fits.tree
mcot/pipe/concrete/trees/dmri.tree
mcot.pipe-0.3.0.dist-info/METADATA
mcot.pipe-0.3.0.dist-info/WHEEL
mcot.pipe-0.3.0.dist-info/entry_points.txt
mcot.pipe-0.3.0.dist-info/namespace_packages.txt
mcot.pipe-0.3.0.dist-info/top_level.txt
mcot.pipe-0.3.0.dist-info/RECORD
